organization/__init__.py
organization/py.typed
organization/_jsii/__init__.py
organization/_jsii/cdk-library-aws-organization@0.4.69.jsii.tgz
renovosolutions.aws_cdk_aws_organization-0.4.69.dist-info/LICENSE
renovosolutions.aws_cdk_aws_organization-0.4.69.dist-info/METADATA
renovosolutions.aws_cdk_aws_organization-0.4.69.dist-info/WHEEL
renovosolutions.aws_cdk_aws_organization-0.4.69.dist-info/top_level.txt
renovosolutions.aws_cdk_aws_organization-0.4.69.dist-info/RECORD
