Metadata-Version: 2.1
Name: renovosolutions.aws-cdk-aws-organization
Version: 0.4.69
Summary: AWS CDK Construct Library to manage specific AWS Organization resources
Home-page: https://github.com/RenovoSolutions/cdk-library-aws-organization.git
Author: Renovo Solutions<webmaster+cdk@renovo1.com>
License: Apache-2.0
Project-URL: Source, https://github.com/RenovoSolutions/cdk-library-aws-organization.git
Platform: UNKNOWN
Classifier: Intended Audience :: Developers
Classifier: Operating System :: OS Independent
Classifier: Programming Language :: JavaScript
Classifier: Programming Language :: Python :: 3 :: Only
Classifier: Programming Language :: Python :: 3.6
Classifier: Programming Language :: Python :: 3.7
Classifier: Programming Language :: Python :: 3.8
Classifier: Programming Language :: Python :: 3.9
Classifier: Typing :: Typed
Classifier: Development Status :: 5 - Production/Stable
Classifier: License :: OSI Approved
Requires-Python: >=3.6
License-File: LICENSE
Requires-Dist: aws-cdk-lib (<3.0.0,>=2.19.0)
Requires-Dist: constructs (<11.0.0,>=10.0.5)
Requires-Dist: jsii (<2.0.0,>=1.55.1)
Requires-Dist: publication (>=0.0.3)
